mllm/__init__.py
mllm/chat.py
mllm/chat_logger.py
mllm/config.py
mllm/env_utils.py
mllm/provider_switch.py
mllm/special_models.py
mllm/structured_chat.py
mllm/cache/__init__.py
mllm/cache/cache_embedding.py
mllm/cache/cache_kv.py
mllm/cache/cache_service.py
mllm/cache/conn_pool.py
mllm/debug/__init__.py
mllm/display/__init__.py
mllm/display/show_html.py
mllm/embedding/__init__.py
mllm/embedding/get.py
mllm/embedding/vector_store.py
mllm/setup/__init__.py
mllm/setup/inject_dotenv.py
mllm/setup/inject_rc.py
mllm/setup/run_app.py
mllm/setup/setup_app.py
mllm/setup/wizard.py
mllm/utils/__init__.py
mllm/utils/ipython.py
mllm/utils/logger.py
mllm/utils/maps.py
mllm/utils/parser.py
mllm/utils/retry.py
minimalllm-1.2.2.dist-info/METADATA
minimalllm-1.2.2.dist-info/WHEEL
minimalllm-1.2.2.dist-info/top_level.txt
minimalllm-1.2.2.dist-info/RECORD
