Metadata-Version: 2.4
Name: MinimalLLM
Version: 1.2.2
Summary: Minimal toolkit for LLM
Author: Zijian Zhang
Project-URL: Homepage, https://github.com/EvoEvolver/MinimalLLM
Project-URL: Issues, https://github.com/EvoEvolver/MinimalLLM/issues
Requires-Python: >=3.8
Requires-Dist: numpy<=1.26
Requires-Dist: httpx
Requires-Dist: pillow
Requires-Dist: litellm<=1.69.0
Requires-Dist: tenacity
Requires-Dist: tqdm
Requires-Dist: json2html
Requires-Dist: pytest
Provides-Extra: dev
Requires-Dist: pytest; extra == "dev"
